cases/case_1.py
cases/case_2.py
cases/case_3.py
cases/case_4.py
mola/__init__.py
mola/configs.py
mola/handles.py
mola/layouts.py
PyMOL_advance-0.1.dist-info/LICENSE
PyMOL_advance-0.1.dist-info/METADATA
PyMOL_advance-0.1.dist-info/WHEEL
PyMOL_advance-0.1.dist-info/top_level.txt
PyMOL_advance-0.1.dist-info/RECORD
