Metadata-Version: 2.1
Name: PyMOL-advance
Version: 0.1
Summary: PyMOL-advance: high-level interfaces from structure data to publication-standard figures
Home-page: https://github.com/BGI-SynBio/PyMOL-advance
Author: Haoling Zhang
Author-email: zhanghaoling@genomics.cn
License: GPL
Keywords: PyMOL,batch visualization
Platform: UNKNOWN
Classifier: License :: OSI Approved :: GNU General Public License (GPL)
Classifier: Programming Language :: Python :: 3
Classifier: Operating System :: OS Independent
License-File: LICENSE
Requires-Dist: numpy
Requires-Dist: pymol
Requires-Dist: pillow
Requires-Dist: biopython
Requires-Dist: matplotlib
